{
  "weeks": [
    {
      "x": 0.0,
      "l": 1.0,
      "m": 33.8787,
      "s": 0.03496,
      "sd3neg": 30.3,
      "sd2neg": 31.5,
      "sd1neg": 32.7,
      "sd0": 33.9,
      "sd1": 35.1,
      "sd2": 36.2,
      "sd3": 37.4
    },
    {
      "x": 1.0,
      "l": 1.0,
      "m": 34.5529,
      "s": 0.03374,
      "sd3neg": 31.1,
      "sd2neg": 32.2,
      "sd1neg": 33.4,
      "sd0": 34.6,
      "sd1": 35.7,
      "sd2": 36.9,
      "sd3": 38.1
    },
    {
      "x": 2.0,
      "l": 1.0,
      "m": 35.2272,
      "s": 0.03251,
      "sd3neg": 31.8,
      "sd2neg": 32.9,
      "sd1neg": 34.1,
      "sd0": 35.2,
      "sd1": 36.4,
      "sd2": 37.5,
      "sd3": 38.7
    },
    {
      "x": 3.0,
      "l": 1.0,
      "m": 35.843,
      "s": 0.03231,
      "sd3neg": 32.4,
      "sd2neg": 33.5,
      "sd1neg": 34.7,
      "sd0": 35.8,
      "sd1": 37.0,
      "sd2": 38.2,
      "sd3": 39.3
    },
    {
      "x": 4.0,
      "l": 1.0,
      "m": 36.3761,
      "s": 0.03215,
      "sd3neg": 32.9,
      "sd2neg": 34.0,
      "sd1neg": 35.2,
      "sd0": 36.4,
      "sd1": 37.5,
      "sd2": 38.7,
      "sd3": 39.9
    },
    {
      "x": 5.0,
      "l": 1.0,
      "m": 36.8472,
      "s": 0.03202,
      "sd3neg": 33.3,
      "sd2neg": 34.5,
      "sd1neg": 35.7,
      "sd0": 36.8,
      "sd1": 38.0,
      "sd2": 39.2,
      "sd3": 40.4
    },
    {
      "x": 6.0,
      "l": 1.0,
      "m": 37.2711,
      "s": 0.03191,
      "sd3neg": 33.7,
      "sd2neg": 34.9,
      "sd1neg": 36.1,
      "sd0": 37.3,
      "sd1": 38.5,
      "sd2": 39.6,
      "sd3": 40.8
    },
    {
      "x": 7.0,
      "l": 1.0,
      "m": 37.6584,
      "s": 0.03182,
      "sd3neg": 34.1,
      "sd2neg": 35.3,
      "sd1neg": 36.5,
      "sd0": 37.7,
      "sd1": 38.9,
      "sd2": 40.1,
      "sd3": 41.3
    },
    {
      "x": 8.0,
      "l": 1.0,
      "m": 38.0167,
      "s": 0.03173,
      "sd3neg": 34.4,
      "sd2neg": 35.6,
      "sd1neg": 36.8,
      "sd0": 38.0,
      "sd1": 39.2,
      "sd2": 40.4,
      "sd3": 41.6
    },
    {
      "x": 9.0,
      "l": 1.0,
      "m": 38.3516,
      "s": 0.03166,
      "sd3neg": 34.7,
      "sd2neg": 35.9,
      "sd1neg": 37.1,
      "sd0": 38.4,
      "sd1": 39.6,
      "sd2": 40.8,
      "sd3": 42.0
    },
    {
      "x": 10.0,
      "l": 1.0,
      "m": 38.6673,
      "s": 0.03158,
      "sd3neg": 35.0,
      "sd2neg": 36.2,
      "sd1neg": 37.4,
      "sd0": 38.7,
      "sd1": 39.9,
      "sd2": 41.1,
      "sd3": 42.3
    },
    {
      "x": 11.0,
      "l": 1.0,
      "m": 38.9661,
      "s": 0.03152,
      "sd3neg": 35.3,
      "sd2neg": 36.5,
      "sd1neg": 37.7,
      "sd0": 39.0,
      "sd1": 40.2,
      "sd2": 41.4,
      "sd3": 42.7
    },
    {
      "x": 12.0,
      "l": 1.0,
      "m": 39.2501,
      "s": 0.03146,
      "sd3neg": 35.5,
      "sd2neg": 36.8,
      "sd1neg": 38.0,
      "sd0": 39.3,
      "sd1": 40.5,
      "sd2": 41.7,
      "sd3": 43.0
    },
    {
      "x": 13.0,
      "l": 1.0,
      "m": 39.521,
      "s": 0.0314,
      "sd3neg": 35.8,
      "sd2neg": 37.0,
      "sd1neg": 38.3,
      "sd0": 39.5,
      "sd1": 40.8,
      "sd2": 42.0,
      "sd3": 43.2
    }
  ],
  "months": [
    {
      "x": 0.0,
      "l": 1.0,
      "m": 33.8787,
      "s": 0.03496,
      "sd3neg": 30.3,
      "sd2neg": 31.5,
      "sd1neg": 32.7,
      "sd0": 33.9,
      "sd1": 35.1,
      "sd2": 36.2,
      "sd3": 37.4
    },
    {
      "x": 1.0,
      "l": 1.0,
      "m": 36.5463,
      "s": 0.0321,
      "sd3neg": 33.0,
      "sd2neg": 34.2,
      "sd1neg": 35.4,
      "sd0": 36.5,
      "sd1": 37.7,
      "sd2": 38.9,
      "sd3": 40.1
    },
    {
      "x": 2.0,
      "l": 1.0,
      "m": 38.2521,
      "s": 0.03168,
      "sd3neg": 34.6,
      "sd2neg": 35.8,
      "sd1neg": 37.0,
      "sd0": 38.3,
      "sd1": 39.5,
      "sd2": 40.7,
      "sd3": 41.9
    },
    {
      "x": 3.0,
      "l": 1.0,
      "m": 39.5328,
      "s": 0.0314,
      "sd3neg": 35.8,
      "sd2neg": 37.1,
      "sd1neg": 38.3,
      "sd0": 39.5,
      "sd1": 40.8,
      "sd2": 42.0,
      "sd3": 43.3
    },
    {
      "x": 4.0,
      "l": 1.0,
      "m": 40.5817,
      "s": 0.03119,
      "sd3neg": 36.8,
      "sd2neg": 38.1,
      "sd1neg": 39.3,
      "sd0": 40.6,
      "sd1": 41.8,
      "sd2": 43.1,
      "sd3": 44.4
    },
    {
      "x": 5.0,
      "l": 1.0,
      "m": 41.459,
      "s": 0.03102,
      "sd3neg": 37.6,
      "sd2neg": 38.9,
      "sd1neg": 40.2,
      "sd0": 41.5,
      "sd1": 42.7,
      "sd2": 44.0,
      "sd3": 45.3
    },
    {
      "x": 6.0,
      "l": 1.0,
      "m": 42.1995,
      "s": 0.03087,
      "sd3neg": 38.3,
      "sd2neg": 39.6,
      "sd1neg": 40.9,
      "sd0": 42.2,
      "sd1": 43.5,
      "sd2": 44.8,
      "sd3": 46.1
    },
    {
      "x": 7.0,
      "l": 1.0,
      "m": 42.829,
      "s": 0.03075,
      "sd3neg": 38.9,
      "sd2neg": 40.2,
      "sd1neg": 41.5,
      "sd0": 42.8,
      "sd1": 44.1,
      "sd2": 45.5,
      "sd3": 46.8
    },
    {
      "x": 8.0,
      "l": 1.0,
      "m": 43.3671,
      "s": 0.03063,
      "sd3neg": 39.4,
      "sd2neg": 40.7,
      "sd1neg": 42.0,
      "sd0": 43.4,
      "sd1": 44.7,
      "sd2": 46.0,
      "sd3": 47.4
    },
    {
      "x": 9.0,
      "l": 1.0,
      "m": 43.83,
      "s": 0.03053,
      "sd3neg": 39.8,
      "sd2neg": 41.2,
      "sd1neg": 42.5,
      "sd0": 43.8,
      "sd1": 45.2,
      "sd2": 46.5,
      "sd3": 47.8
    },
    {
      "x": 10.0,
      "l": 1.0,
      "m": 44.2319,
      "s": 0.03044,
      "sd3neg": 40.2,
      "sd2neg": 41.5,
      "sd1neg": 42.9,
      "sd0": 44.2,
      "sd1": 45.6,
      "sd2": 46.9,
      "sd3": 48.3
    },
    {
      "x": 11.0,
      "l": 1.0,
      "m": 44.5844,
      "s": 0.03035,
      "sd3neg": 40.5,
      "sd2neg": 41.9,
      "sd1neg": 43.2,
      "sd0": 44.6,
      "sd1": 45.9,
      "sd2": 47.3,
      "sd3": 48.6
    },
    {
      "x": 12.0,
      "l": 1.0,
      "m": 44.8965,
      "s": 0.03027,
      "sd3neg": 40.8,
      "sd2neg": 42.2,
      "sd1neg": 43.5,
      "sd0": 44.9,
      "sd1": 46.3,
      "sd2": 47.6,
      "sd3": 49.0
    },
    {
      "x": 13.0,
      "l": 1.0,
      "m": 45.1752,
      "s": 0.03019,
      "sd3neg": 41.1,
      "sd2neg": 42.4,
      "sd1neg": 43.8,
      "sd0": 45.2,
      "sd1": 46.5,
      "sd2": 47.9,
      "sd3": 49.3
    },
    {
      "x": 14.0,
      "l": 1.0,
      "m": 45.4265,
      "s": 0.03012,
      "sd3neg": 41.3,
      "sd2neg": 42.7,
      "sd1neg": 44.1,
      "sd0": 45.4,
      "sd1": 46.8,
      "sd2": 48.2,
      "sd3": 49.5
    },
    {
      "x": 15.0,
      "l": 1.0,
      "m": 45.6551,
      "s": 0.03006,
      "sd3neg": 41.5,
      "sd2neg": 42.9,
      "sd1neg": 44.3,
      "sd0": 45.7,
      "sd1": 47.0,
      "sd2": 48.4,
      "sd3": 49.8
    },
    {
      "x": 16.0,
      "l": 1.0,
      "m": 45.865,
      "s": 0.02999,
      "sd3neg": 41.7,
      "sd2neg": 43.1,
      "sd1neg": 44.5,
      "sd0": 45.9,
      "sd1": 47.2,
      "sd2": 48.6,
      "sd3": 50.0
    },
    {
      "x": 17.0,
      "l": 1.0,
      "m": 46.0598,
      "s": 0.02993,
      "sd3neg": 41.9,
      "sd2neg": 43.3,
      "sd1neg": 44.7,
      "sd0": 46.1,
      "sd1": 47.4,
      "sd2": 48.8,
      "sd3": 50.2
    },
    {
      "x": 18.0,
      "l": 1.0,
      "m": 46.2424,
      "s": 0.02987,
      "sd3neg": 42.1,
      "sd2neg": 43.5,
      "sd1neg": 44.9,
      "sd0": 46.2,
      "sd1": 47.6,
      "sd2": 49.0,
      "sd3": 50.4
    },
    {
      "x": 19.0,
      "l": 1.0,
      "m": 46.4152,
      "s": 0.02982,
      "sd3neg": 42.3,
      "sd2neg": 43.6,
      "sd1neg": 45.0,
      "sd0": 46.4,
      "sd1": 47.8,
      "sd2": 49.2,
      "sd3": 50.6
    },
    {
      "x": 20.0,
      "l": 1.0,
      "m": 46.5801,
      "s": 0.02977,
      "sd3neg": 42.4,
      "sd2neg": 43.8,
      "sd1neg": 45.2,
      "sd0": 46.6,
      "sd1": 48.0,
      "sd2": 49.4,
      "sd3": 50.7
    },
    {
      "x": 21.0,
      "l": 1.0,
      "m": 46.7384,
      "s": 0.02972,
      "sd3neg": 42.6,
      "sd2neg": 44.0,
      "sd1neg": 45.3,
      "sd0": 46.7,
      "sd1": 48.1,
      "sd2": 49.5,
      "sd3": 50.9
    },
    {
      "x": 22.0,
      "l": 1.0,
      "m": 46.8913,
      "s": 0.02967,
      "sd3neg": 42.7,
      "sd2neg": 44.1,
      "sd1neg": 45.5,
      "sd0": 46.9,
      "sd1": 48.3,
      "sd2": 49.7,
      "sd3": 51.1
    },
    {
      "x": 23.0,
      "l": 1.0,
      "m": 47.0391,
      "s": 0.02962,
      "sd3neg": 42.9,
      "sd2neg": 44.3,
      "sd1neg": 45.6,
      "sd0": 47.0,
      "sd1": 48.4,
      "sd2": 49.8,
      "sd3": 51.2
    },
    {
      "x": 24.0,
      "l": 1.0,
      "m": 47.1822,
      "s": 0.02957,
      "sd3neg": 43.0,
      "sd2neg": 44.4,
      "sd1neg": 45.8,
      "sd0": 47.2,
      "sd1": 48.6,
      "sd2": 50.0,
      "sd3": 51.4
    },
    {
      "x": 25.0,
      "l": 1.0,
      "m": 47.3204,
      "s": 0.02953,
      "sd3neg": 43.1,
      "sd2neg": 44.5,
      "sd1neg": 45.9,
      "sd0": 47.3,
      "sd1": 48.7,
      "sd2": 50.1,
      "sd3": 51.5
    },
    {
      "x": 26.0,
      "l": 1.0,
      "m": 47.4536,
      "s": 0.02949,
      "sd3neg": 43.3,
      "sd2neg": 44.7,
      "sd1neg": 46.1,
      "sd0": 47.5,
      "sd1": 48.9,
      "sd2": 50.3,
      "sd3": 51.7
    },
    {
      "x": 27.0,
      "l": 1.0,
      "m": 47.5817,
      "s": 0.02945,
      "sd3neg": 43.4,
      "sd2neg": 44.8,
      "sd1neg": 46.2,
      "sd0": 47.6,
      "sd1": 49.0,
      "sd2": 50.4,
      "sd3": 51.8
    },
    {
      "x": 28.0,
      "l": 1.0,
      "m": 47.7045,
      "s": 0.02941,
      "sd3neg": 43.5,
      "sd2neg": 44.9,
      "sd1neg": 46.3,
      "sd0": 47.7,
      "sd1": 49.1,
      "sd2": 50.5,
      "sd3": 51.9
    },
    {
      "x": 29.0,
      "l": 1.0,
      "m": 47.8219,
      "s": 0.02937,
      "sd3neg": 43.6,
      "sd2neg": 45.0,
      "sd1neg": 46.4,
      "sd0": 47.8,
      "sd1": 49.2,
      "sd2": 50.6,
      "sd3": 52.0
    },
    {
      "x": 30.0,
      "l": 1.0,
      "m": 47.934,
      "s": 0.02933,
      "sd3neg": 43.7,
      "sd2neg": 45.1,
      "sd1neg": 46.5,
      "sd0": 47.9,
      "sd1": 49.3,
      "sd2": 50.7,
      "sd3": 52.2
    },
    {
      "x": 31.0,
      "l": 1.0,
      "m": 48.041,
      "s": 0.02929,
      "sd3neg": 43.8,
      "sd2neg": 45.2,
      "sd1neg": 46.6,
      "sd0": 48.0,
      "sd1": 49.4,
      "sd2": 50.9,
      "sd3": 52.3
    },
    {
      "x": 32.0,
      "l": 1.0,
      "m": 48.1432,
      "s": 0.02926,
      "sd3neg": 43.9,
      "sd2neg": 45.3,
      "sd1neg": 46.7,
      "sd0": 48.1,
      "sd1": 49.6,
      "sd2": 51.0,
      "sd3": 52.4
    },
    {
      "x": 33.0,
      "l": 1.0,
      "m": 48.2408,
      "s": 0.02922,
      "sd3neg": 44.0,
      "sd2neg": 45.4,
      "sd1neg": 46.8,
      "sd0": 48.2,
      "sd1": 49.7,
      "sd2": 51.1,
      "sd3": 52.5
    },
    {
      "x": 34.0,
      "l": 1.0,
      "m": 48.3343,
      "s": 0.02919,
      "sd3neg": 44.1,
      "sd2neg": 45.5,
      "sd1neg": 46.9,
      "sd0": 48.3,
      "sd1": 49.7,
      "sd2": 51.2,
      "sd3": 52.6
    },
    {
      "x": 35.0,
      "l": 1.0,
      "m": 48.4239,
      "s": 0.02915,
      "sd3neg": 44.2,
      "sd2neg": 45.6,
      "sd1neg": 47.0,
      "sd0": 48.4,
      "sd1": 49.8,
      "sd2": 51.2,
      "sd3": 52.7
    },
    {
      "x": 36.0,
      "l": 1.0,
      "m": 48.5099,
      "s": 0.02912,
      "sd3neg": 44.3,
      "sd2neg": 45.7,
      "sd1neg": 47.1,
      "sd0": 48.5,
      "sd1": 49.9,
      "sd2": 51.3,
      "sd3": 52.7
    },
    {
      "x": 37.0,
      "l": 1.0,
      "m": 48.5926,
      "s": 0.02909,
      "sd3neg": 44.4,
      "sd2neg": 45.8,
      "sd1neg": 47.2,
      "sd0": 48.6,
      "sd1": 50.0,
      "sd2": 51.4,
      "sd3": 52.8
    },
    {
      "x": 38.0,
      "l": 1.0,
      "m": 48.6722,
      "s": 0.02906,
      "sd3neg": 44.4,
      "sd2neg": 45.8,
      "sd1neg": 47.3,
      "sd0": 48.7,
      "sd1": 50.1,
      "sd2": 51.5,
      "sd3": 52.9
    },
    {
      "x": 39.0,
      "l": 1.0,
      "m": 48.7489,
      "s": 0.02903,
      "sd3neg": 44.5,
      "sd2neg": 45.9,
      "sd1neg": 47.3,
      "sd0": 48.7,
      "sd1": 50.2,
      "sd2": 51.6,
      "sd3": 53.0
    },
    {
      "x": 40.0,
      "l": 1.0,
      "m": 48.8228,
      "s": 0.029,
      "sd3neg": 44.6,
      "sd2neg": 46.0,
      "sd1neg": 47.4,
      "sd0": 48.8,
      "sd1": 50.2,
      "sd2": 51.7,
      "sd3": 53.1
    },
    {
      "x": 41.0,
      "l": 1.0,
      "m": 48.8941,
      "s": 0.02897,
      "sd3neg": 44.6,
      "sd2neg": 46.1,
      "sd1neg": 47.5,
      "sd0": 48.9,
      "sd1": 50.3,
      "sd2": 51.7,
      "sd3": 53.1
    },
    {
      "x": 42.0,
      "l": 1.0,
      "m": 48.9629,
      "s": 0.02894,
      "sd3neg": 44.7,
      "sd2neg": 46.1,
      "sd1neg": 47.5,
      "sd0": 49.0,
      "sd1": 50.4,
      "sd2": 51.8,
      "sd3": 53.2
    },
    {
      "x": 43.0,
      "l": 1.0,
      "m": 49.0294,
      "s": 0.02891,
      "sd3neg": 44.8,
      "sd2neg": 46.2,
      "sd1neg": 47.6,
      "sd0": 49.0,
      "sd1": 50.4,
      "sd2": 51.9,
      "sd3": 53.3
    },
    {
      "x": 44.0,
      "l": 1.0,
      "m": 49.0937,
      "s": 0.02888,
      "sd3neg": 44.8,
      "sd2neg": 46.3,
      "sd1neg": 47.7,
      "sd0": 49.1,
      "sd1": 50.5,
      "sd2": 51.9,
      "sd3": 53.3
    },
    {
      "x": 45.0,
      "l": 1.0,
      "m": 49.156,
      "s": 0.02886,
      "sd3neg": 44.9,
      "sd2neg": 46.3,
      "sd1neg": 47.7,
      "sd0": 49.2,
      "sd1": 50.6,
      "sd2": 52.0,
      "sd3": 53.4
    },
    {
      "x": 46.0,
      "l": 1.0,
      "m": 49.2164,
      "s": 0.02883,
      "sd3neg": 45.0,
      "sd2neg": 46.4,
      "sd1neg": 47.8,
      "sd0": 49.2,
      "sd1": 50.6,
      "sd2": 52.1,
      "sd3": 53.5
    },
    {
      "x": 47.0,
      "l": 1.0,
      "m": 49.2751,
      "s": 0.0288,
      "sd3neg": 45.0,
      "sd2neg": 46.4,
      "sd1neg": 47.9,
      "sd0": 49.3,
      "sd1": 50.7,
      "sd2": 52.1,
      "sd3": 53.5
    },
    {
      "x": 48.0,
      "l": 1.0,
      "m": 49.3321,
      "s": 0.02878,
      "sd3neg": 45.1,
      "sd2neg": 46.5,
      "sd1neg": 47.9,
      "sd0": 49.3,
      "sd1": 50.8,
      "sd2": 52.2,
      "sd3": 53.6
    },
    {
      "x": 49.0,
      "l": 1.0,
      "m": 49.3877,
      "s": 0.02875,
      "sd3neg": 45.1,
      "sd2neg": 46.5,
      "sd1neg": 48.0,
      "sd0": 49.4,
      "sd1": 50.8,
      "sd2": 52.2,
      "sd3": 53.6
    },
    {
      "x": 50.0,
      "l": 1.0,
      "m": 49.4419,
      "s": 0.02873,
      "sd3neg": 45.2,
      "sd2neg": 46.6,
      "sd1neg": 48.0,
      "sd0": 49.4,
      "sd1": 50.9,
      "sd2": 52.3,
      "sd3": 53.7
    },
    {
      "x": 51.0,
      "l": 1.0,
      "m": 49.4947,
      "s": 0.0287,
      "sd3neg": 45.2,
      "sd2neg": 46.7,
      "sd1neg": 48.1,
      "sd0": 49.5,
      "sd1": 50.9,
      "sd2": 52.3,
      "sd3": 53.8
    },
    {
      "x": 52.0,
      "l": 1.0,
      "m": 49.5464,
      "s": 0.02868,
      "sd3neg": 45.3,
      "sd2neg": 46.7,
      "sd1neg": 48.1,
      "sd0": 49.5,
      "sd1": 51.0,
      "sd2": 52.4,
      "sd3": 53.8
    },
    {
      "x": 53.0,
      "l": 1.0,
      "m": 49.5969,
      "s": 0.02865,
      "sd3neg": 45.3,
      "sd2neg": 46.8,
      "sd1neg": 48.2,
      "sd0": 49.6,
      "sd1": 51.0,
      "sd2": 52.4,
      "sd3": 53.9
    },
    {
      "x": 54.0,
      "l": 1.0,
      "m": 49.6464,
      "s": 0.02863,
      "sd3neg": 45.4,
      "sd2neg": 46.8,
      "sd1neg": 48.2,
      "sd0": 49.6,
      "sd1": 51.1,
      "sd2": 52.5,
      "sd3": 53.9
    },
    {
      "x": 55.0,
      "l": 1.0,
      "m": 49.6947,
      "s": 0.02861,
      "sd3neg": 45.4,
      "sd2neg": 46.9,
      "sd1neg": 48.3,
      "sd0": 49.7,
      "sd1": 51.1,
      "sd2": 52.5,
      "sd3": 54.0
    },
    {
      "x": 56.0,
      "l": 1.0,
      "m": 49.7421,
      "s": 0.02859,
      "sd3neg": 45.5,
      "sd2neg": 46.9,
      "sd1neg": 48.3,
      "sd0": 49.7,
      "sd1": 51.2,
      "sd2": 52.6,
      "sd3": 54.0
    },
    {
      "x": 57.0,
      "l": 1.0,
      "m": 49.7885,
      "s": 0.02856,
      "sd3neg": 45.5,
      "sd2neg": 46.9,
      "sd1neg": 48.4,
      "sd0": 49.8,
      "sd1": 51.2,
      "sd2": 52.6,
      "sd3": 54.1
    },
    {
      "x": 58.0,
      "l": 1.0,
      "m": 49.8341,
      "s": 0.02854,
      "sd3neg": 45.6,
      "sd2neg": 47.0,
      "sd1neg": 48.4,
      "sd0": 49.8,
      "sd1": 51.3,
      "sd2": 52.7,
      "sd3": 54.1
    },
    {
      "x": 59.0,
      "l": 1.0,
      "m": 49.8789,
      "s": 0.02852,
      "sd3neg": 45.6,
      "sd2neg": 47.0,
      "sd1neg": 48.5,
      "sd0": 49.9,
      "sd1": 51.3,
      "sd2": 52.7,
      "sd3": 54.1
    },
    {
      "x": 60.0,
      "l": 1.0,
      "m": 49.9229,
      "s": 0.0285,
      "sd3neg": 45.7,
      "sd2neg": 47.1,
      "sd1neg": 48.5,
      "sd0": 49.9,
      "sd1": 51.3,
      "sd2": 52.8,
      "sd3": 54.2
    }
  ]
}